djorm_ext_filtered_contenttypes-0.4.1.dist-info/DESCRIPTION.rst
djorm_ext_filtered_contenttypes-0.4.1.dist-info/METADATA
djorm_ext_filtered_contenttypes-0.4.1.dist-info/RECORD
djorm_ext_filtered_contenttypes-0.4.1.dist-info/WHEEL
djorm_ext_filtered_contenttypes-0.4.1.dist-info/metadata.json
djorm_ext_filtered_contenttypes-0.4.1.dist-info/top_level.txt
filtered_contenttypes/__init__.py
filtered_contenttypes/fields.py
filtered_contenttypes/utils.py
