Metadata-Version: 2.0
Name: djorm-ext-filtered-contenttypes
Version: 0.4.1
Summary: GenericForeignKey with filtering capabilities for Django ORM + PostgreSQL
Home-page: https://github.com/mpasternak/djorm-ext-filtered-contenttypes
Author: Michal Pasternak
Author-email: michal.dtz@gmail.com
License: MIT
Platform: OS Independent
Classifier: Operating System :: OS Independent
Classifier: Environment :: Web Environment
Classifier: Framework :: Django
Classifier: License :: OSI Approved :: MIT License
Classifier: Intended Audience :: Developers
Classifier: Programming Language :: Python
Classifier: Programming Language :: Python :: 2
Classifier: Programming Language :: Python :: 2.7
Classifier: Programming Language :: Python :: 3
Classifier: Programming Language :: Python :: 3.6
Classifier: Topic :: Software Development :: Libraries
Classifier: Topic :: Utilities
Requires-Dist: Django (<1.12,>=1.7)
